netdisc/__init__.py
netdisc/cisco_nxos.py
netdisc/common.py
netdisc/juniper.py
netdisc/network.py
netdisc/paloalto_panos.py
netdisc-0.1.0.dist-info/WHEEL
netdisc-0.1.0.dist-info/METADATA
netdisc-0.1.0.dist-info/RECORD
